akson/__init__.py
akson/cli/main.py
akson-0.3.3.dist-info/LICENSE
akson-0.3.3.dist-info/METADATA
akson-0.3.3.dist-info/WHEEL
akson-0.3.3.dist-info/entry_points.txt
akson-0.3.3.dist-info/RECORD
