Metadata-Version: 2.1
Name: akson
Version: 0.3.3
Summary: CLI and libary for Akson AI agents
Home-page: https://akson.ai
Keywords: ai,agents
Author: Akson AI
Author-email: hi@akson.ai
Requires-Python: >=3.12,<4.0
Classifier: Programming Language :: Python :: 3
Classifier: Programming Language :: Python :: 3.12
Requires-Dist: click (>=8.1.7,<9.0.0)
Requires-Dist: fastapi (>=0.110.0)
Requires-Dist: httpx (>=0.24.0)
Requires-Dist: prompt-toolkit (>=3.0.47,<4.0.0)
Requires-Dist: pydantic (>=2.7.3,<3.0.0)
Requires-Dist: uvicorn (>=0.25.0)
Project-URL: Repository, https://github.com/akson-ai/akson-python
